setup.py
itamake/__init__.py
itamake/itaMake.py
itamake/terminal.py
itamake.egg-info/PKG-INFO
itamake.egg-info/SOURCES.txt
itamake.egg-info/dependency_links.txt
itamake.egg-info/entry_points.txt
itamake.egg-info/requires.txt
itamake.egg-info/top_level.txt