Metadata-Version: 1.0
Name: itamake
Version: 0.3.0
Summary: A stripped down cmsMake which *only* makes, nothing more.
Home-page: https://github.com/algorithm-ninja/ita-make
Author: Algorithm Ninja
Author-email: algorithm@ninja
License: GPL3
Platform: UNKNOWN
